huaweicloudsdksdrs/__init__.py
huaweicloudsdksdrs/v1/__init__.py
huaweicloudsdksdrs/v1/sdrs_async_client.py
huaweicloudsdksdrs/v1/sdrs_client.py
huaweicloudsdksdrs/v1/model/__init__.py
huaweicloudsdksdrs/v1/model/add_protected_instance_nic_request.py
huaweicloudsdksdrs/v1/model/add_protected_instance_nic_response.py
huaweicloudsdksdrs/v1/model/add_protected_instance_tags_request.py
huaweicloudsdksdrs/v1/model/add_protected_instance_tags_response.py
huaweicloudsdksdrs/v1/model/attach_protected_instance_replication_request.py
huaweicloudsdksdrs/v1/model/attach_protected_instance_replication_response.py
huaweicloudsdksdrs/v1/model/batch_add_tags_request.py
huaweicloudsdksdrs/v1/model/batch_add_tags_request_body.py
huaweicloudsdksdrs/v1/model/batch_add_tags_response.py
huaweicloudsdksdrs/v1/model/batch_create_protected_instances_request.py
huaweicloudsdksdrs/v1/model/batch_create_protected_instances_request_body.py
huaweicloudsdksdrs/v1/model/batch_create_protected_instances_request_params.py
huaweicloudsdksdrs/v1/model/batch_create_protected_instances_response.py
huaweicloudsdksdrs/v1/model/batch_delete_protected_instances_request.py
huaweicloudsdksdrs/v1/model/batch_delete_protected_instances_request_body.py
huaweicloudsdksdrs/v1/model/batch_delete_protected_instances_response.py
huaweicloudsdksdrs/v1/model/batch_delete_tags_request.py
huaweicloudsdksdrs/v1/model/batch_delete_tags_request_body.py
huaweicloudsdksdrs/v1/model/batch_delete_tags_response.py
huaweicloudsdksdrs/v1/model/create_disaster_recovery_drill_request.py
huaweicloudsdksdrs/v1/model/create_disaster_recovery_drill_request_body.py
huaweicloudsdksdrs/v1/model/create_disaster_recovery_drill_request_params.py
huaweicloudsdksdrs/v1/model/create_disaster_recovery_drill_response.py
huaweicloudsdksdrs/v1/model/create_protected_instance_request.py
huaweicloudsdksdrs/v1/model/create_protected_instance_request_body.py
huaweicloudsdksdrs/v1/model/create_protected_instance_request_params.py
huaweicloudsdksdrs-3.1.184.dist-info/METADATA
huaweicloudsdksdrs-3.1.184.dist-info/WHEEL
huaweicloudsdksdrs-3.1.184.dist-info/licenses/LICENSE
huaweicloudsdksdrs-3.1.184.dist-info/RECORD
